README.md
pyproject.toml
setup.py
hyperdata.egg-info/PKG-INFO
hyperdata.egg-info/SOURCES.txt
hyperdata.egg-info/dependency_links.txt
hyperdata.egg-info/not-zip-safe
hyperdata.egg-info/top_level.txt
mlplatform_lib/__init__.py
mlplatform_lib/hyperdata_api.py
mlplatform_lib/hyperdata_client.py
mlplatform_lib/pre_check_base.py
mlplatform_lib/dataclass/__init__.py
mlplatform_lib/dataclass/column_of_table_from_default_source.py
mlplatform_lib/dataclass/data_object.py
mlplatform_lib/dataclass/insert_tuple_object.py
mlplatform_lib/dataclass/table_column_info.py
mlplatform_lib/dataclass/table_desc_info.py
mlplatform_lib/dataclass/table_from_default_datasource_info.py
mlplatform_lib/predefinedai/__init__.py
mlplatform_lib/predefinedai/pre_check_predefinedai.py
mlplatform_lib/predefinedai/predefinedai_api.py
mlplatform_lib/predefinedai/predefinedai_template_test.py
tests/__init__.py
tests/conftest.py
tests/hyperdata_pytest.py
tests/predefinedai_pytest.py