Metadata-Version: 1.2
Name: hyperdata
Version: 8.4.0.0
Summary: hyperdata
Home-page: UNKNOWN
Author: hyperdata
Author-email: mansu_kim@tmax.co.kr
License: UNKNOWN
Keywords: hyperdata
Platform: UNKNOWN
Classifier: Programming Language :: Python :: 3.7
Requires-Python: >=3.7
